py_mmut_rdf/__init__.py
py_mmut_rdf/mmut.py
py_mmut_rdf/mmut.ttl
py_mmut_rdf/ontology_reader.py
py_mmut_rdf-0.0.2.dist-info/METADATA
py_mmut_rdf-0.0.2.dist-info/WHEEL
py_mmut_rdf-0.0.2.dist-info/licenses/LICENSE
py_mmut_rdf-0.0.2.dist-info/RECORD
