Metadata-Version: 2.4
Name: py_mmut_rdf
Version: 0.0.2
Summary: Python library providing RDF ontology definitions for SysML.
License: MIT
License-File: LICENSE
Author: Dirk Friedenberger
Author-email: projekte@frittenburger.de
Requires-Python: >=3.9,<4.0
Classifier: License :: OSI Approved :: MIT License
Classifier: Programming Language :: Python :: 3
Classifier: Programming Language :: Python :: 3.9
Classifier: Programming Language :: Python :: 3.10
Classifier: Programming Language :: Python :: 3.11
Classifier: Programming Language :: Python :: 3.12
Classifier: Programming Language :: Python :: 3.13
Classifier: Programming Language :: Python :: 3.14
Requires-Dist: rdflib (>=6.0)
Project-URL: Homepage, https://github.com/dfriedenberger/mmut-rdf-model
